LICENSE
MANIFEST.in
README.rst
requirements-docs.txt
requirements.txt
setup.py
async_truckersmp.egg-info/PKG-INFO
async_truckersmp.egg-info/SOURCES.txt
async_truckersmp.egg-info/dependency_links.txt
async_truckersmp.egg-info/requires.txt
async_truckersmp.egg-info/top_level.txt
truckersmp/__init__.py
truckersmp/base.py
truckersmp/cache.py
truckersmp/endpoints.py
truckersmp/exceptions.py
truckersmp/web.py
truckersmp/models/__init__.py
truckersmp/models/ban.py
truckersmp/models/event.py
truckersmp/models/player.py
truckersmp/models/rules.py
truckersmp/models/server.py
truckersmp/models/version.py
truckersmp/models/vtc.py