Metadata-Version: 2.1
Name: async-truckersmp
Version: 0.2.3
Summary: An asynchronous Python API wrapper for TruckersMP.
Home-page: https://github.com/SamNuttall/Async-TruckersMP
Author: Sam Nuttall
Author-email: dev@samln.dev
License: MIT
Keywords: truckersmp
Platform: UNKNOWN
Classifier: Development Status :: 3 - Alpha
Classifier: Intended Audience :: Developers
Classifier: Operating System :: OS Independent
Classifier: License :: OSI Approved :: MIT License
Classifier: Programming Language :: Python :: 3
License-File: LICENSE
